README.rst
setup.py
django_wf.egg-info/PKG-INFO
django_wf.egg-info/SOURCES.txt
django_wf.egg-info/dependency_links.txt
django_wf.egg-info/requires.txt
django_wf.egg-info/top_level.txt
django_workflow/__init__.py
django_workflow/admin.py
django_workflow/conditions.py
django_workflow/models.py
django_workflow/settings.py
django_workflow/tests.py
django_workflow/urls.py
django_workflow/utils.py
django_workflow/workflow.py
django_workflow/wsgi.py
django_workflow/management/__init__.py
django_workflow/management/commands/__init__.py
django_workflow/management/commands/autotransitions.py
django_workflow/migrations/0001_initial.py
django_workflow/migrations/__init__.py