Metadata-Version: 1.1
Name: django-wf
Version: 0.9.1
Summary: A simple database driven workflow engine
Home-page: https://github.com/dani0805/django_workflow
Author: Daniele Bernardini
Author-email: db@intranetstandard.com
License: BSD-3-Clause
Keywords: workflow state machine development
Platform: UNKNOWN
Classifier: Development Status :: 3 - Alpha
Classifier: Intended Audience :: Developers
Classifier: Topic :: Software Development :: Build Tools
Classifier: License :: OSI Approved :: BSD License
Classifier: Programming Language :: Python :: 2
Classifier: Programming Language :: Python :: 2.7
